{
  "schema": "investor.log-envelope.v2",
  "id": "4539ca2a-2fb6-4415-91d5-15602d55fb47",
  "kind": "alpha_discovery",
  "asOfDate": "20260301",
  "generatedAt": "2026-03-01T03:26:14.192Z",
  "producer": {
    "component": "experiments.alpha_mining_experiments.discoverAlphaFactors"
  },
  "payload": {
    "schema": "investor.alpha-discovery.v3",
    "date": "20260301",
    "generatedAt": "2026-03-01T03:26:14.192Z",
    "stage": "DISCOVERY_PRECHECK",
    "scoreType": "LINGUISTIC_PRECHECK",
    "evidence": {
      "sampleSize": 2,
      "selectedCount": 1,
      "selectionRate": 0.5
    },
    "quality": {
      "completeness": "COMPLETE",
      "missingFields": []
    },
    "selected": [
      "ALPHA-MACRO-F7EC19F9"
    ],
    "candidates": [
      {
        "id": "ALPHA-HFT-3C1A4312",
        "description": "Causal Mechanism (CAMEF) Hypothesis (HFT Engineer)",
        "reasoning": "CLAIM: Structural drift identification via Causal Mechanism (CAMEF) and causality. [REASONING] The HFT Engineer persona targets intervention using a counterfactual approach. Optimized for mechanism regimes.",
        "status": "REJECTED",
        "rejectReason": "RPA: High linguistic risk profile detected.",
        "recency": "2026-03-01T03:26:14.192Z",
        "scores": {
          "priority": 0.581923076923077,
          "plausibility": 0.55,
          "riskAdjusted": 0.5,
          "novelty": 0.7846153846153846
        },
        "generation": 1,
        "mutationType": "NEW_SEED",
        "ast": {
          "type": "operator",
          "name": "DIV",
          "left": {
            "type": "variable",
            "name": "kg_centrality"
          },
          "right": {
            "type": "operator",
            "name": "DIV",
            "left": {
              "type": "variable",
              "name": "close"
            },
            "right": {
              "type": "constant",
              "value": 0.68
            }
          }
        }
      },
      {
        "id": "ALPHA-MACRO-F7EC19F9",
        "description": "10-K Intelligence 2.0 (Mission) Hypothesis (Macro Strategist)",
        "reasoning": "CLAIM: High-precision ai_exposure forecasting using 10-K Intelligence 2.0 (Mission). [REASONING] A segment_sentiment model that uses itemization to filter noise during kg_centrality periods. Proposed by Macro Strategist.",
        "status": "SELECTED",
        "recency": "2026-03-01T03:26:14.192Z",
        "scores": {
          "priority": 0.6319230769230769,
          "plausibility": 0.65,
          "riskAdjusted": 0.5,
          "novelty": 0.7846153846153846
        },
        "generation": 1,
        "mutationType": "NEW_SEED",
        "ast": {
          "type": "operator",
          "name": "SUB",
          "left": {
            "type": "constant",
            "value": 0.56
          },
          "right": {
            "type": "constant",
            "value": 3.27
          }
        }
      }
    ],
    "universe": [
      "1333",
      "1377",
      "1379",
      "1407",
      "1417",
      "1605",
      "1663",
      "1719",
      "1721",
      "1766",
      "1786",
      "1801",
      "1802",
      "1803",
      "1805",
      "1808",
      "1812",
      "1813",
      "1815",
      "1822",
      "1833",
      "1852",
      "1860",
      "1879",
      "1882",
      "1885",
      "1887",
      "1899",
      "1934",
      "1941",
      "1944",
      "1945",
      "1959",
      "1963",
      "1973",
      "1979",
      "2001",
      "2002",
      "2127",
      "2148",
      "2153",
      "2154",
      "2160",
      "2168",
      "2170",
      "2193",
      "2217",
      "2282",
      "2292",
      "2296",
      "2317",
      "2326",
      "2327",
      "2337",
      "2379",
      "2412",
      "2427",
      "2433",
      "2489",
      "2492",
      "2501",
      "2531",
      "2579",
      "2587",
      "2594",
      "2607",
      "2664",
      "2678",
      "2681",
      "2715",
      "2730",
      "2733",
      "2734",
      "2737",
      "2752",
      "2760",
      "2767",
      "2768",
      "2784",
      "2801",
      "2809",
      "2810",
      "2871",
      "2914",
      "2930",
      "2933",
      "2980",
      "3002",
      "3036",
      "3040",
      "3046",
      "3048",
      "3076",
      "3088",
      "3097",
      "3099",
      "3105",
      "3106",
      "3116",
      "3134",
      "3156",
      "3167",
      "3180",
      "3182",
      "3222",
      "3254",
      "3289",
      "3319",
      "3328",
      "3349",
      "3371",
      "3377",
      "3387",
      "3391",
      "3397",
      "3401",
      "3407",
      "3436",
      "3479",
      "3482"
    ],
    "startedAt": "2026-03-01T03:26:14.169Z"
  },
  "derived": false,
  "lineage": {
    "sourceSchema": "investor.alpha-discovery.v3",
    "sourceBucket": "unified"
  }
}